pyCoopGame/Core.py
pyCoopGame/CostGap.py
pyCoopGame/Create_game.py
pyCoopGame/Maali.py
pyCoopGame/Nucleolus.py
pyCoopGame/Shapley.py
pyCoopGame/Validate_game.py
pyCoopGame/__init__.py
pyCoopGame-0.0.6.dist-info/LICENSE
pyCoopGame-0.0.6.dist-info/METADATA
pyCoopGame-0.0.6.dist-info/WHEEL
pyCoopGame-0.0.6.dist-info/top_level.txt
pyCoopGame-0.0.6.dist-info/RECORD
