Metadata-Version: 2.1
Name: pyCoopGame
Version: 0.0.6
Summary: various profit allocation methods from cooperative game theory
Home-page: https://github.com/flechtenberg/pyCoopGame
Author: Fabian Lechtenberg
Author-email: fabian.lechtenberg@upc.edu
Classifier: Programming Language :: Python :: 3
Classifier: License :: OSI Approved :: BSD License
Classifier: Operating System :: OS Independent
Requires-Python: >=3.9, <=3.12
License-File: LICENSE
